{"cameraMode":{"drawMode":0,"name":"Shaded","section":"Shading Mode"},"sceneLighting":true,"audioPlay":false,"sceneViewState":{"showFog":true,"showMaterialUpdate":false,"showSkybox":true,"showFlares":true,"showImageEffects":true,"showParticleSystems":true},"in2DMode":false,"pivot":{"x":282.7407531738281,"y":-2.80133056640625,"z":112.962646484375},"rotation":{"x":0.23102140426635743,"y":-0.7410301566123962,"z":0.3126998245716095,"w":0.5474696159362793},"size":51.04249954223633,"orthographic":false}